Workbook

Sheet START_HERE
B2: PHARMACEUTICAL SALES DATA ANALYTICS
B3: iNeuBytes VIIP | Course DAINB10926 | Quantity analysis, not revenue
B5: PROJECT STATUS & HOW TO USE THIS WORKBOOK
B6: Source rows | C6: 2,106 daily rows | 02 Jan 2014 to 08 Oct 2019
B7: Main metric | C7: Total recorded quantity: 127,595.50; average per observed day: 60.59
B8: Interactive dashboard | C8: Open Dashboard. Change the Year and Category yellow drop-down cells; Excel recalculates KPI cards and charts.
B9: Native PivotTables | C9: Pivot-style result sheets are included. If your mentor requires actual Excel PivotTable objects, follow Excel_Step_by_Step.md and insert them from Long_Daily.
B10: Monthly data caution | C10: Monthly results are derived from daily data. The supplied monthly CSV has 33 months that do not reconcile within 0.01 across all categories.
B11: Partial periods | C11: January 2014 and October 2019 are incomplete. They are labelled and excluded from the complete-month trend.
B14: WORKBOOK MAP
B15: Raw_Daily | C15: Original daily fields as supplied; no source values overwritten.
B16: Clean_Daily | C16: ISO-style Excel dates, category quantities, Total_Quantity formulas, calendar fields, partial-month flag.
B17: Long_Daily | C17: Tidy one-row-per-date/category table for native PivotTables and BI practice.
B18: Formula_Examples | C18: Working SUM, AVERAGE, COUNTIF and SUMIFS examples with plain-English explanations.
B19: Monthly_Summary | C19: Monthly totals recalculated from daily data, coverage flags and month-over-month results.
B20: Category_Summary | C20: Category contribution, variability, zero days and historical demand baseline.
B21: Weekday_Summary | C21: Total and average quantity by weekday.
B22: Data_Quality | C22: Missing values, duplicates, date checks and source reconciliation notes.
B23: Monthly_Reconciliation | C23: Supplied monthly totals compared with totals derived from daily data.
B24: Dashboard | C24: Formula-driven KPI cards and charts with Year/Category selectors.
B27: Important: “sales” means source-recorded quantity. The dataset has no price, revenue, profit, current stock, supplier lead time, or expiry fields. Do not turn these historical values directly into purchase orders.
B30: Kaggle dataset source and ATC descriptions
B32: Student: [enter name] Registration No.: [enter registration number] Repository: [create using required naming rule]

Sheet Raw_Daily
A1: datum | B1: M01AB | C1: M01AE | D1: N02BA | E1: N02BE | F1: N05B | G1: N05C | H1: R03 | I1: R06 | J1: Year | K1: Month | L1: Hour | M1: Weekday Name
A2: 1/2/2014 | B2: 0 | C2: 3.67 | D2: 3.4 | E2: 32.4 | F2: 7 | G2: 0 | H2: 0 | I2: 2 | J2: 2014 | K2: 1 | L2: 248 | M2: Thursday
A3: 1/3/2014 | B3: 8 | C3: 4 | D3: 4.4 | E3: 50.6 | F3: 16 | G3: 0 | H3: 20 | I3: 4 | J3: 2014 | K3: 1 | L3: 276 | M3: Friday
A4: 1/4/2014 | B4: 2 | C4: 1 | D4: 6.5 | E4: 61.85 | F4: 10 | G4: 0 | H4: 9 | I4: 1 | J4: 2014 | K4: 1 | L4: 276 | M4: Saturday
A5: 1/5/2014 | B5: 4 | C5: 3 | D5: 7 | E5: 41.1 | F5: 8 | G5: 0 | H5: 3 | I5: 0 | J5: 2014 | K5: 1 | L5: 276 | M5: Sunday
A6: 1/6/2014 | B6: 5 | C6: 1 | D6: 4.5 | E6: 21.7 | F6: 16 | G6: 2 | H6: 6 | I6: 2 | J6: 2014 | K6: 1 | L6: 276 | M6: Monday
A7: 1/7/2014 | B7: 0 | C7: 0 | D7: 0 | E7: 0 | F7: 0 | G7: 0 | H7: 0 | I7: 0 | J7: 2014 | K7: 1 | L7: 276 | M7: Tuesday
A8: 1/8/2014 | B8: 5.33 | C8: 3 | D8: 10.5 | E8: 26.4 | F8: 19 | G8: 1 | H8: 10 | I8: 0 | J8: 2014 | K8: 1 | L8: 276 | M8: Wednesday
A9: 1/9/2014 | B9: 7 | C9: 1.68 | D9: 8 | E9: 25 | F9: 16 | G9: 0 | H9: 3 | I9: 2 | J9: 2014 | K9: 1 | L9: 276 | M9: Thursday
A10: 1/10/2014 | B10: 5 | C10: 2 | D10: 2 | E10: 53.3 | F10: 15 | G10: 2 | H10: 0 | I10: 2 | J10: 2014 | K10: 1 | L10: 276 | M10: Friday
A11: 1/11/2014 | B11: 5 | C11: 4.34 | D11: 10.4 | E11: 52.3 | F11: 14 | G11: 0 | H11: 1 | I11: 0.2 | J11: 2014 | K11: 1 | L11: 276 | M11: Saturday
A12: 1/12/2014 | B12: 2 | C12: 0.66 | D12: 2.5 | E12: 12 | F12: 8 | G12: 0 | H12: 1 | I12: 1 | J12: 2014 | K12: 1 | L12: 276 | M12: Sunday
A13: 1/13/2014 | B13: 7.34 | C13: 7.66 | D13: 6.2 | E13: 52 | F13: 9 | G13: 0 | H13: 7 | I13: 1 | J13: 2014 | K13: 1 | L13: 276 | M13: Monday
... A2107: 10/8/2019 | B2107: 0.33 | C2107: 1.73 | D2107: 0.5 | E2107: 44.3 | F2107: 20 | G2107: 2 | H2107: 2 | I2107: 0 | J2107: 2019 | K2107: 10 | L2107: 190 | M2107: Tuesday

Sheet Clean_Daily
A1: Sale_Date | B1: M01AB | C1: M01AE | D1: N02BA | E1: N02BE | F1: N05B | G1: N05C | H1: R03 | I1: R06 | J1: Total_Quantity | K1: Year | L1: Month_Number | M1: Month_Start | N1: Month_Name | O1: Weekday_Number | P1: Weekday_Name | Q1: Is_Complete_Month
A2: 41641 | B2: 0 | C2: 3.67 | D2: 3.4 | E2: 32.4 | F2: 7 | G2: 0 | H2: 0 | I2: 2 | J2: =SUM(B2:I2) -> 48.47 | K2: 2014 | L2: 1 | M2: 41640 | N2: January | O2: 4 | P2: Thursday | Q2: FALSE
A3: 41642 | B3: 8 | C3: 4 | D3: 4.4 | E3: 50.6 | F3: 16 | G3: 0 | H3: 20 | I3: 4 | J3: =SUM(B3:I3) -> 107 | K3: 2014 | L3: 1 | M3: 41640 | N3: January | O3: 5 | P3: Friday | Q3: FALSE
A4: 41643 | B4: 2 | C4: 1 | D4: 6.5 | E4: 61.85 | F4: 10 | G4: 0 | H4: 9 | I4: 1 | J4: =SUM(B4:I4) -> 91.35 | K4: 2014 | L4: 1 | M4: 41640 | N4: January | O4: 6 | P4: Saturday | Q4: FALSE
A5: 41644 | B5: 4 | C5: 3 | D5: 7 | E5: 41.1 | F5: 8 | G5: 0 | H5: 3 | I5: 0 | J5: =SUM(B5:I5) -> 66.1 | K5: 2014 | L5: 1 | M5: 41640 | N5: January | O5: 7 | P5: Sunday | Q5: FALSE
A6: 41645 | B6: 5 | C6: 1 | D6: 4.5 | E6: 21.7 | F6: 16 | G6: 2 | H6: 6 | I6: 2 | J6: =SUM(B6:I6) -> 58.2 | K6: 2014 | L6: 1 | M6: 41640 | N6: January | O6: 1 | P6: Monday | Q6: FALSE
A7: 41646 | B7: 0 | C7: 0 | D7: 0 | E7: 0 | F7: 0 | G7: 0 | H7: 0 | I7: 0 | J7: =SUM(B7:I7) -> 0 | K7: 2014 | L7: 1 | M7: 41640 | N7: January | O7: 2 | P7: Tuesday | Q7: FALSE
A8: 41647 | B8: 5.33 | C8: 3 | D8: 10.5 | E8: 26.4 | F8: 19 | G8: 1 | H8: 10 | I8: 0 | J8: =SUM(B8:I8) -> 75.23 | K8: 2014 | L8: 1 | M8: 41640 | N8: January | O8: 3 | P8: Wednesday | Q8: FALSE
A9: 41648 | B9: 7 | C9: 1.68 | D9: 8 | E9: 25 | F9: 16 | G9: 0 | H9: 3 | I9: 2 | J9: =SUM(B9:I9) -> 62.68 | K9: 2014 | L9: 1 | M9: 41640 | N9: January | O9: 4 | P9: Thursday | Q9: FALSE
A10: 41649 | B10: 5 | C10: 2 | D10: 2 | E10: 53.3 | F10: 15 | G10: 2 | H10: 0 | I10: 2 | J10: =SUM(B10:I10) -> 81.3 | K10: 2014 | L10: 1 | M10: 41640 | N10: January | O10: 5 | P10: Friday | Q10: FALSE
A11: 41650 | B11: 5 | C11: 4.34 | D11: 10.4 | E11: 52.3 | F11: 14 | G11: 0 | H11: 1 | I11: 0.2 | J11: =SUM(B11:I11) -> 87.24 | K11: 2014 | L11: 1 | M11: 41640 | N11: January | O11: 6 | P11: Saturday | Q11: FALSE
A12: 41651 | B12: 2 | C12: 0.66 | D12: 2.5 | E12: 12 | F12: 8 | G12: 0 | H12: 1 | I12: 1 | J12: =SUM(B12:I12) -> 27.16 | K12: 2014 | L12: 1 | M12: 41640 | N12: January | O12: 7 | P12: Sunday | Q12: FALSE
A13: 41652 | B13: 7.34 | C13: 7.66 | D13: 6.2 | E13: 52 | F13: 9 | G13: 0 | H13: 7 | I13: 1 | J13: =SUM(B13:I13) -> 90.2 | K13: 2014 | L13: 1 | M13: 41640 | N13: January | O13: 1 | P13: Monday | Q13: FALSE
... A2107: 43746 | B2107: 0.33 | C2107: 1.73 | D2107: 0.5 | E2107: 44.3 | F2107: 20 | G2107: 2 | H2107: 2 | I2107: 0 | J2107: =SUM(B2107:I2107) -> 70.86 | K2107: 2019 | L2107: 10 | M2107: 43739 | N2107: October | O2107: 2 | P2107: Tuesday | Q2107: FALSE

Sheet Long_Daily
A1: Sale_Date | B1: Year | C1: Month_Number | D1: Month_Start | E1: Month_Name | F1: Weekday_Number | G1: Weekday_Name | H1: ATC_Category | I1: Category_Description | J1: Quantity | K1: Is_Complete_Month
A2: 41641 | B2: 2014 | C2: 1 | D2: 41640 | E2: January | F2: 4 | G2: Thursday | H2: M01AB | I2: Anti-inflammatory and antirheumatic products, non-steroids — acetic acid derivatives and related substances | J2: 0 | K2: FALSE
A3: 41641 | B3: 2014 | C3: 1 | D3: 41640 | E3: January | F3: 4 | G3: Thursday | H3: M01AE | I3: Anti-inflammatory and antirheumatic products, non-steroids — propionic acid derivatives | J3: 3.67 | K3: FALSE
A4: 41641 | B4: 2014 | C4: 1 | D4: 41640 | E4: January | F4: 4 | G4: Thursday | H4: N02BA | I4: Other analgesics and antipyretics — salicylic acid and derivatives | J4: 3.4 | K4: FALSE
A5: 41641 | B5: 2014 | C5: 1 | D5: 41640 | E5: January | F5: 4 | G5: Thursday | H5: N02BE | I5: Other analgesics and antipyretics — pyrazolones and anilides | J5: 32.4 | K5: FALSE
A6: 41641 | B6: 2014 | C6: 1 | D6: 41640 | E6: January | F6: 4 | G6: Thursday | H6: N05B | I6: Psycholeptics — anxiolytic drugs | J6: 7 | K6: FALSE
A7: 41641 | B7: 2014 | C7: 1 | D7: 41640 | E7: January | F7: 4 | G7: Thursday | H7: N05C | I7: Psycholeptics — hypnotics and sedatives | J7: 0 | K7: FALSE
A8: 41641 | B8: 2014 | C8: 1 | D8: 41640 | E8: January | F8: 4 | G8: Thursday | H8: R03 | I8: Drugs for obstructive airway diseases | J8: 0 | K8: FALSE
A9: 41641 | B9: 2014 | C9: 1 | D9: 41640 | E9: January | F9: 4 | G9: Thursday | H9: R06 | I9: Antihistamines for systemic use | J9: 2 | K9: FALSE
A10: 41642 | B10: 2014 | C10: 1 | D10: 41640 | E10: January | F10: 5 | G10: Friday | H10: M01AB | I10: Anti-inflammatory and antirheumatic products, non-steroids — acetic acid derivatives and related substances | J10: 8 | K10: FALSE
A11: 41642 | B11: 2014 | C11: 1 | D11: 41640 | E11: January | F11: 5 | G11: Friday | H11: M01AE | I11: Anti-inflammatory and antirheumatic products, non-steroids — propionic acid derivatives | J11: 4 | K11: FALSE
A12: 41642 | B12: 2014 | C12: 1 | D12: 41640 | E12: January | F12: 5 | G12: Friday | H12: N02BA | I12: Other analgesics and antipyretics — salicylic acid and derivatives | J12: 4.4 | K12: FALSE
A13: 41642 | B13: 2014 | C13: 1 | D13: 41640 | E13: January | F13: 5 | G13: Friday | H13: N02BE | I13: Other analgesics and antipyretics — pyrazolones and anilides | J13: 50.6 | K13: FALSE
... A16849: 43746 | B16849: 2019 | C16849: 10 | D16849: 43739 | E16849: October | F16849: 2 | G16849: Tuesday | H16849: R06 | I16849: Antihistamines for systemic use | J16849: 0 | K16849: FALSE

Sheet Formula_Examples
A1: EXCEL FORMULAS — PRACTICAL EXAMPLES
A3: Metric | B3: Calculated value | C3: Formula used in column B | D3: What it teaches
A4: Total quantity | B4: =SUM(Clean_Daily!J2:J2107) -> 127595.5 | C4: =SUM(Clean_Daily!J2:J2107) | D4: SUM adds every daily total.
A5: Average daily quantity | B5: =AVERAGE(Clean_Daily!J2:J2107) -> 60.586659 | C5: =AVERAGE(Clean_Daily!J2:J2107) | D5: AVERAGE gives the mean per observed day.
A6: Observed days | B6: =COUNT(Clean_Daily!A2:A2107) -> 2106 | C6: =COUNT(Clean_Daily!A2:A2107) | D6: COUNT counts numeric Excel dates.
A7: N02BE days above 50 | B7: =COUNTIF(Clean_Daily!E2:E2107,">50") -> 227 | C7: =COUNTIF(Clean_Daily!E2:E2107,">50") | D7: COUNTIF counts rows that meet one condition.
A8: N02BE total | B8: =SUM(Clean_Daily!E2:E2107) -> 63005.403 | C8: =SUM(Clean_Daily!E2:E2107) | D8: SUM also works for one category column.
A9: N05C zero-quantity days | B9: =COUNTIF(Clean_Daily!G2:G2107,0) -> 1430 | C9: =COUNTIF(Clean_Daily!G2:G2107,0) | D9: Useful for identifying intermittent demand.
A10: January 2019 total | B10: =SUMIFS(Clean_Daily!J2:J2107,Clean_Daily!K2:K2107,2019,Clean_Daily!L2:L2107,1) -> 2875.158 | C10: =SUMIFS(Clean_Daily!J2:J2107,Clean_Daily!K2:K2107,2019,Clean_Daily!L2:L2107,1) | D10: SUMIFS adds values only when both Year=2019 and Month=1.
A11: 2018 total | B11: =SUMIFS(Clean_Daily!J2:J2107,Clean_Daily!K2:K2107,2018) -> 22884.561 | C11: =SUMIFS(Clean_Daily!J2:J2107,Clean_Daily!K2:K2107,2018) | D11: SUMIFS with one condition.
A12: Saturday observed days | B12: =COUNTIF(Clean_Daily!P2:P2107,"Saturday") -> 301 | C12: =COUNTIF(Clean_Daily!P2:P2107,"Saturday") | D12: COUNTIF also works with text.
A13: Saturday total | B13: =SUMIFS(Clean_Daily!J2:J2107,Clean_Daily!P2:P2107,"Saturday") -> 19767.594 | C13: =SUMIFS(Clean_Daily!J2:J2107,Clean_Daily!P2:P2107,"Saturday") | D13: SUMIFS with a weekday condition.
A16: Column map used above: J = Total_Quantity, E = N02BE, G = N05C, K = Year, L = Month_Number, P = Weekday_Name. Formulas recalculate when opened in Excel. Values are cached so the initial results remain visible in file previews.

Sheet Monthly_Summary
A1: Month_Start | B1: Year | C1: Month_Number | D1: Month_Name | E1: Days_Observed | F1: Expected_Days | G1: Is_Complete_Month | H1: Total_Quantity | I1: Average_Daily_Quantity | J1: Previous_Month_Quantity | K1: MoM_Growth_Percent
A2: 41640 | B2: 2014 | C2: 1 | D2: January | E2: 30 | F2: 31 | G2: FALSE | H2: =SUMIFS(Clean_Daily!$J$2:$J$2107,Clean_Daily!$M$2:$M$2107,A2) -> 1801.11 | I2: =H2/E2 -> 60.037
A3: 41671 | B3: 2014 | C3: 2 | D3: February | E3: 28 | F3: 28 | G3: TRUE | H3: =SUMIFS(Clean_Daily!$J$2:$J$2107,Clean_Daily!$M$2:$M$2107,A3) -> 1974.47 | I3: =H3/E3 -> 70.516786 | J3: =H2 -> 1801.11
A4: 41699 | B4: 2014 | C4: 3 | D4: March | E4: 31 | F4: 31 | G4: TRUE | H4: =SUMIFS(Clean_Daily!$J$2:$J$2107,Clean_Daily!$M$2:$M$2107,A4) -> 1606.72 | I4: =H4/E4 -> 51.829677 | J4: =H3 -> 1974.47 | K4: =IF(AND(G4=TRUE,G3=TRUE),100*(H4/J4-1),"") -> -18.625251
A5: 41730 | B5: 2014 | C5: 4 | D5: April | E5: 30 | F5: 30 | G5: TRUE | H5: =SUMIFS(Clean_Daily!$J$2:$J$2107,Clean_Daily!$M$2:$M$2107,A5) -> 1423.925 | I5: =H5/E5 -> 47.464167 | J5: =H4 -> 1606.72 | K5: =IF(AND(G5=TRUE,G4=TRUE),100*(H5/J5-1),"") -> -11.376905
A6: 41760 | B6: 2014 | C6: 5 | D6: May | E6: 31 | F6: 31 | G6: TRUE | H6: =SUMIFS(Clean_Daily!$J$2:$J$2107,Clean_Daily!$M$2:$M$2107,A6) -> 1506.303 | I6: =H6/E6 -> 48.590419 | J6: =H5 -> 1423.925 | K6: =IF(AND(G6=TRUE,G5=TRUE),100*(H6/J6-1),"") -> 5.7852766
A7: 41791 | B7: 2014 | C7: 6 | D7: June | E7: 30 | F7: 30 | G7: TRUE | H7: =SUMIFS(Clean_Daily!$J$2:$J$2107,Clean_Daily!$M$2:$M$2107,A7) -> 1390.205 | I7: =H7/E7 -> 46.340167 | J7: =H6 -> 1506.303 | K7: =IF(AND(G7=TRUE,G6=TRUE),100*(H7/J7-1),"") -> -7.7074798
A8: 41821 | B8: 2014 | C8: 7 | D8: July | E8: 31 | F8: 31 | G8: TRUE | H8: =SUMIFS(Clean_Daily!$J$2:$J$2107,Clean_Daily!$M$2:$M$2107,A8) -> 1332.37 | I8: =H8/E8 -> 42.979677 | J8: =H7 -> 1390.205 | K8: =IF(AND(G8=TRUE,G7=TRUE),100*(H8/J8-1),"") -> -4.1601778
A9: 41852 | B9: 2014 | C9: 8 | D9: August | E9: 31 | F9: 31 | G9: TRUE | H9: =SUMIFS(Clean_Daily!$J$2:$J$2107,Clean_Daily!$M$2:$M$2107,A9) -> 1452.52 | I9: =H9/E9 -> 46.855484 | J9: =H8 -> 1332.37 | K9: =IF(AND(G9=TRUE,G8=TRUE),100*(H9/J9-1),"") -> 9.0177653
A10: 41883 | B10: 2014 | C10: 9 | D10: September | E10: 30 | F10: 30 | G10: TRUE | H10: =SUMIFS(Clean_Daily!$J$2:$J$2107,Clean_Daily!$M$2:$M$2107,A10) -> 1804.594 | I10: =H10/E10 -> 60.153133 | J10: =H9 -> 1452.52 | K10: =IF(AND(G10=TRUE,G9=TRUE),100*(H10/J10-1),"") -> 24.23884
A11: 41913 | B11: 2014 | C11: 10 | D11: October | E11: 31 | F11: 31 | G11: TRUE | H11: =SUMIFS(Clean_Daily!$J$2:$J$2107,Clean_Daily!$M$2:$M$2107,A11) -> 2081.9957 | I11: =H11/E11 -> 67.161151 | J11: =H10 -> 1804.594 | K11: =IF(AND(G11=TRUE,G10=TRUE),100*(H11/J11-1),"") -> 15.371972
A12: 41944 | B12: 2014 | C12: 11 | D12: November | E12: 30 | F12: 30 | G12: TRUE | H12: =SUMIFS(Clean_Daily!$J$2:$J$2107,Clean_Daily!$M$2:$M$2107,A12) -> 1770.64 | I12: =H12/E12 -> 59.021333 | J12: =H11 -> 2081.9957 | K12: =IF(AND(G12=TRUE,G11=TRUE),100*(H12/J12-1),"") -> -14.954675
A13: 41974 | B13: 2014 | C13: 12 | D13: December | E13: 31 | F13: 31 | G13: TRUE | H13: =SUMIFS(Clean_Daily!$J$2:$J$2107,Clean_Daily!$M$2:$M$2107,A13) -> 2093.485 | I13: =H13/E13 -> 67.531774 | J13: =H12 -> 1770.64 | K13: =IF(AND(G13=TRUE,G12=TRUE),100*(H13/J13-1),"") -> 18.233238
A14: 42005 | B14: 2015 | C14: 1 | D14: January | E14: 31 | F14: 31 | G14: TRUE | H14: =SUMIFS(Clean_Daily!$J$2:$J$2107,Clean_Daily!$M$2:$M$2107,A14) -> 2157.749 | I14: =H14/E14 -> 69.604806 | J14: =H13 -> 2093.485 | K14: =IF(AND(G14=TRUE,G13=TRUE),100*(H14/J14-1),"") -> 3.0697139
A15: 42036 | B15: 2015 | C15: 2 | D15: February | E15: 28 | F15: 28 | G15: TRUE | H15: =SUMIFS(Clean_Daily!$J$2:$J$2107,Clean_Daily!$M$2:$M$2107,A15) -> 1831.532 | I15: =H15/E15 -> 65.411857 | J15: =H14 -> 2157.749 | K15: =IF(AND(G15=TRUE,G14=TRUE),100*(H15/J15-1),"") -> -15.118394
... A70: 43709 | B70: 2019 | C70: 9 | D70: September | E70: 30 | F70: 30 | G70: TRUE | H70: =SUMIFS(Clean_Daily!$J$2:$J$2107,Clean_Daily!$M$2:$M$2107,A70) -> 1824.8037 | I70: =H70/E70 -> 60.826789 | J70: =H69 -> 1377.779 | K70: =IF(AND(G70=TRUE,G69=TRUE),100*(H70/J70-1),"") -> 32.44531
A71: 43739 | B71: 2019 | C71: 10 | D71: October | E71: 8 | F71: 31 | G71: FALSE | H71: =SUMIFS(Clean_Daily!$J$2:$J$2107,Clean_Daily!$M$2:$M$2107,A71) -> 538.6 | I71: =H71/E71 -> 67.325 | J71: =H70 -> 1824.8037

Sheet Category_Summary
A1: Rank_by_Total_Quantity | B1: ATC_Category | C1: Category_Description | D1: Total_Quantity | E1: Share_of_Total_Percent | F1: Average_Daily_Quantity | G1: Median_Daily_Quantity | H1: StdDev_Daily_Quantity | I1: Coefficient_of_Variation | J1: P95_Daily_Quantity | K1: Maximum_Daily_Quantity | L1: Zero_Quantity_Days | M1: Zero_Day_Percent
A2: 1 | B2: N02BE | C2: Other analgesics and antipyretics — pyrazolones and anilides | D2: =SUM(Clean_Daily!E2:E2107) -> 63005.403 | E2: =100*D2/SUM($D$2:$D$9) -> 49.379015 | F2: =AVERAGE(Clean_Daily!E2:E2107) -> 29.917095 | G2: =MEDIAN(Clean_Daily!E2:E2107) -> 26.9 | H2: =STDEV.S(Clean_Daily!E2:E2107) -> 15.590966 | I2: 0.52113901 | J2: 59.9375 | K2: 161 | L2: =COUNTIF(Clean_Daily!E2:E2107,0) -> 26 | M2: =100*L2/2106 -> 1.2345679
A3: 2 | B3: N05B | C3: Psycholeptics — anxiolytic drugs | D3: =SUM(Clean_Daily!F2:F2107) -> 18645.737 | E3: =100*D3/SUM($D$2:$D$9) -> 14.613162 | F3: =AVERAGE(Clean_Daily!F2:F2107) -> 8.8536265 | G3: =MEDIAN(Clean_Daily!F2:F2107) -> 8 | H3: =STDEV.S(Clean_Daily!F2:F2107) -> 5.6056047 | I3: 0.63314222 | J3: 19 | K3: 54.833333 | L3: =COUNTIF(Clean_Daily!F2:F2107,0) -> 43 | M3: =100*L3/2106 -> 2.0417854
A4: 3 | B4: R03 | C4: Drugs for obstructive airway diseases | D4: =SUM(Clean_Daily!H2:H2107) -> 11608.823 | E4: =100*D4/SUM($D$2:$D$9) -> 9.0981442 | F4: =AVERAGE(Clean_Daily!H2:H2107) -> 5.5122616 | G4: =MEDIAN(Clean_Daily!H2:H2107) -> 4 | H4: =STDEV.S(Clean_Daily!H2:H2107) -> 6.4287364 | I4: 1.1662611 | J4: 20 | K4: 45 | L4: =COUNTIF(Clean_Daily!H2:H2107,0) -> 484 | M4: =100*L4/2106 -> 22.981956
A5: 4 | B5: M01AB | C5: Anti-inflammatory and antirheumatic products, non-steroids — acetic acid derivatives and related substances | D5: =SUM(Clean_Daily!B2:B2107) -> 10600.937 | E5: =100*D5/SUM($D$2:$D$9) -> 8.3082372 | F5: =AVERAGE(Clean_Daily!B2:B2107) -> 5.0336833 | G5: =MEDIAN(Clean_Daily!B2:B2107) -> 4.99 | H5: =STDEV.S(Clean_Daily!B2:B2107) -> 2.7375785 | I5: 0.54385195 | J5: 10 | K5: 17.34 | L5: =COUNTIF(Clean_Daily!B2:B2107,0) -> 40 | M5: =100*L5/2106 -> 1.8993352
A6: 5 | B6: M01AE | C6: Anti-inflammatory and antirheumatic products, non-steroids — propionic acid derivatives | D6: =SUM(Clean_Daily!C2:C2107) -> 8204.6186 | E6: =100*D6/SUM($D$2:$D$9) -> 6.4301785 | F6: =AVERAGE(Clean_Daily!C2:C2107) -> 3.8958303 | G6: =MEDIAN(Clean_Daily!C2:C2107) -> 3.67 | H6: =STDEV.S(Clean_Daily!C2:C2107) -> 2.1333366 | I6: 0.54759485 | J6: 7.66 | K6: 14.463 | L6: =COUNTIF(Clean_Daily!C2:C2107,0) -> 36 | M6: =100*L6/2106 -> 1.7094017
A7: 6 | B7: N02BA | C7: Other analgesics and antipyretics — salicylic acid and derivatives | D7: =SUM(Clean_Daily!D2:D2107) -> 8172.209 | E7: =100*D7/SUM($D$2:$D$9) -> 6.4047782 | F7: =AVERAGE(Clean_Daily!D2:D2107) -> 3.8804411 | G7: =MEDIAN(Clean_Daily!D2:D2107) -> 3.5 | H7: =STDEV.S(Clean_Daily!D2:D2107) -> 2.3840102 | I7: 0.61436578 | J7: 8 | K7: 16 | L7: =COUNTIF(Clean_Daily!D2:D2107,0) -> 78 | M7: =100*L7/2106 -> 3.7037037
A8: 7 | B8: R06 | C8: Antihistamines for systemic use | D8: =SUM(Clean_Daily!I2:I2107) -> 6107.8175 | E8: =100*D8/SUM($D$2:$D$9) -> 4.7868595 | F8: =AVERAGE(Clean_Daily!I2:I2107) -> 2.9001982 | G8: =MEDIAN(Clean_Daily!I2:I2107) -> 2 | H8: =STDEV.S(Clean_Daily!I2:I2107) -> 2.4158159 | I8: 0.83298302 | J8: 8 | K8: 15 | L8: =COUNTIF(Clean_Daily!I2:I2107,0) -> 256 | M8: =100*L8/2106 -> 12.155745
A9: 8 | B9: N05C | C9: Psycholeptics — hypnotics and sedatives | D9: =SUM(Clean_Daily!G2:G2107) -> 1249.9583 | E9: =100*D9/SUM($D$2:$D$9) -> 0.97962569 | F9: =AVERAGE(Clean_Daily!G2:G2107) -> 0.59352248 | G9: =MEDIAN(Clean_Daily!G2:G2107) -> 0 | H9: =STDEV.S(Clean_Daily!G2:G2107) -> 1.0929883 | I9: 1.8415281 | J9: 3 | K9: 9 | L9: =COUNTIF(Clean_Daily!G2:G2107,0) -> 1430 | M9: =100*L9/2106 -> 67.901235

Sheet Weekday_Summary
A1: Weekday_Number | B1: Weekday_Name | C1: Days_Observed | D1: Total_Quantity | E1: Average_Daily_Quantity
A2: 1 | B2: Monday | C2: 301 | D2: 18242.817 | E2: 60.607364
A3: 2 | B3: Tuesday | C3: 301 | D3: 18065.247 | E3: 60.017432
A4: 3 | B4: Wednesday | C4: 300 | D4: 17771.528 | E4: 59.238425
A5: 4 | B5: Thursday | C5: 301 | D5: 17212.389 | E5: 57.184018
A6: 5 | B6: Friday | C6: 301 | D6: 18134.492 | E6: 60.24748
A7: 6 | B7: Saturday | C7: 301 | D7: 19767.594 | E7: 65.673071
A8: 7 | B8: Sunday | C8: 301 | D8: 18401.437 | E8: 61.134343

Sheet Data_Quality
A1: File | B1: Rows | C1: Columns | D1: Missing_Cells | E1: Exact_Duplicate_Rows | F1: Duplicate_Date_or_DateTime_Values | G1: Invalid_Dates | H1: Negative_Category_Values | I1: Start | J1: End | K1: Notes
A2: saleshourly.csv | B2: 50532 | C2: 13 | D2: 0 | E2: 0 | F2: 0 | G2: 0 | H2: 0 | I2: 2014-01-02T08:00:00 | J2: 2019-10-08T19:00:00 | K2: Continuous hourly timestamps; daily totals reconcile within floating-point tolerance.
A3: salesdaily.csv | B3: 2106 | C3: 13 | D3: 0 | E3: 0 | F3: 0 | G3: 0 | H3: 0 | I3: 2014-01-02T00:00:00 | J3: 2019-10-08T00:00:00 | K3: Continuous daily dates. Daily Hour is not time-of-day (only 190, 248, 276), so it is excluded from the clean table.
A4: salesweekly.csv | B4: 302 | C4: 9 | D4: 0 | E4: 0 | F4: 0 | G4: 0 | H4: 0 | I4: 2014-01-05T00:00:00 | J4: 2019-10-13T00:00:00 | K4: All 302 week-ending-Sunday totals reconcile with daily data within 0.01 per category.
A5: salesmonthly.csv | B5: 70 | C5: 9 | D5: 0 | E5: 0 | F5: 0 | G5: 0 | H5: 0 | I5: 2014-01-31T00:00:00 | J5: 2019-10-31T00:00:00 | K5: 37 of 70 months match daily aggregation within 0.01 across all categories; derive monthly trends from daily data.

Sheet Monthly_Reconciliation
A1: Month_Start | B1: Supplied_Monthly_Total | C1: Derived_From_Daily_Total | D1: Difference_Supplied_Minus_Derived | E1: Maximum_Category_Absolute_Difference | F1: Match_Within_0_01
A2: 41640 | B2: 1821.11 | C2: 1801.11 | D2: 20 | E2: 20 | F2: FALSE
A3: 41671 | B3: 1974.47 | C3: 1974.47 | D3: 0 | E3: 9.9475983e-14 | F3: TRUE
A4: 41699 | B4: 1606.72 | C4: 1606.72 | D4: 2.2737368e-13 | E4: 7.1054274e-14 | F4: TRUE
A5: 41730 | B5: 1429.675 | C5: 1423.925 | D5: 5.75 | E5: 5.75 | F5: FALSE
A6: 41760 | B6: 1506.303 | C6: 1506.303 | D6: 0 | E6: 1.1368684e-13 | F6: TRUE
A7: 41791 | B7: 1390.205 | C7: 1390.205 | D7: 2.2737368e-13 | E7: 7.1054274e-14 | F7: TRUE
A8: 41821 | B8: 1332.37 | C8: 1332.37 | D8: 0 | E8: 1.2789769e-13 | F8: TRUE
A9: 41852 | B9: 1499.02 | C9: 1452.52 | D9: 46.5 | E9: 36.5 | F9: FALSE
A10: 41883 | B10: 1814.594 | C10: 1804.594 | D10: 10 | E10: 10 | F10: FALSE
A11: 41913 | B11: 3146.906 | C11: 2081.9957 | D11: 1064.9103 | E11: 783.67812 | F11: FALSE
A12: 41944 | B12: 1770.64 | C12: 1770.64 | D12: 2.2737368e-13 | E12: 4.2632564e-14 | F12: TRUE
A13: 41974 | B13: 2093.485 | C13: 2093.485 | D13: 0 | E13: 4.2632564e-14 | F13: TRUE
... A71: 43739 | B71: 538.6 | C71: 538.6 | D71: 0 | E71: 5.6843419e-14 | F71: TRUE

Sheet Lists
A1: Year_List | B1: Category_List
A2: All | B2: All
A3: 2014 | B3: M01AB
A4: 2015 | B4: M01AE
A5: 2016 | B5: N02BA
A6: 2017 | B6: N02BE
A7: 2018 | B7: N05B
A8: 2019 | B8: N05C
B9: R03
B10: R06

Sheet Dashboard_Data
A1: Month_Start | B1: Is_Complete_Month | C1: Selected_Monthly_Quantity | E1: ATC_Category | F1: Selected_Year_Total | H1: Weekday | I1: Days_in_Selection | J1: Selected_Weekday_Average
A2: M01AB | B2: =IF(Dashboard!$B$3="All",SUM(Clean_Daily!B2:B2107),SUMIFS(Clean_Daily!B2:B2107,Clean_Daily!$K$2:$K$2107,VALUE(Dashboard!$B$3))) -> 10600.937 | C2: =IF(AND(B2=TRUE,OR(Dashboard!$B$3="All",YEAR(A2)=VALUE(Dashboard!$B$3))),IF(Dashboard!$E$3="All",SUMIFS(Clean_Daily!$J$2:$J$2107,Clean_Daily!$M$2:$M$2107,A2),SUMIFS(INDEX(Clean_Daily!$B$2:$I$2107,0,MATCH(Dashboard!$E$3,Clean_Daily!$B$1:$I$1,0)),Clean_Daily!$M$2:$M$2107,A2)),NA()) -> #N/A | H2: Monday | I2: =IF(Dashboard!$B$3="All",COUNTIF(Clean_Daily!$P$2:$P$2107,H2),COUNTIFS(Clean_Daily!$P$2:$P$2107,H2,Clean_Daily!$K$2:$K$2107,VALUE(Dashboard!$B$3))) -> 301 | J2: =IF(I2=0,0,IF(Dashboard!$E$3="All",IF(Dashboard!$B$3="All",SUMIFS(Clean_Daily!$J$2:$J$2107,Clean_Daily!$P$2:$P$2107,H2),SUMIFS(Clean_Daily!$J$2:$J$2107,Clean_Daily!$P$2:$P$2107,H2,Clean_Daily!$K$2:$K$2107,VALUE(Dashboard!$B$3))),IF(Dashboard!$B$3="All",SUMIFS(INDEX(Clean_Daily!$B$2:$I$2107,0,MATCH(Dashboard!$E$3,Clean_Daily!$B$1:$I$1,0)),Clean_Daily!$P$2:$P$2107,H2),SUMIFS(INDEX(Clean_Daily!$B$2:$I$2107,0,MATCH(Dashboard!$E$3,Clean_Daily!$B$1:$I$1,0)),Clean_Daily!$P$2:$P$2107,H2,Clean_Daily!$K$2:$K$2107,VALUE(Dashboard!$B$3))))/I2) -> 60.607364
A3: M01AE | B3: =IF(Dashboard!$B$3="All",SUM(Clean_Daily!C2:C2107),SUMIFS(Clean_Daily!C2:C2107,Clean_Daily!$K$2:$K$2107,VALUE(Dashboard!$B$3))) -> 8204.6186 | C3: =IF(AND(B3=TRUE,OR(Dashboard!$B$3="All",YEAR(A3)=VALUE(Dashboard!$B$3))),IF(Dashboard!$E$3="All",SUMIFS(Clean_Daily!$J$2:$J$2107,Clean_Daily!$M$2:$M$2107,A3),SUMIFS(INDEX(Clean_Daily!$B$2:$I$2107,0,MATCH(Dashboard!$E$3,Clean_Daily!$B$1:$I$1,0)),Clean_Daily!$M$2:$M$2107,A3)),NA()) -> 1974.47 | H3: Tuesday | I3: =IF(Dashboard!$B$3="All",COUNTIF(Clean_Daily!$P$2:$P$2107,H3),COUNTIFS(Clean_Daily!$P$2:$P$2107,H3,Clean_Daily!$K$2:$K$2107,VALUE(Dashboard!$B$3))) -> 301 | J3: =IF(I3=0,0,IF(Dashboard!$E$3="All",IF(Dashboard!$B$3="All",SUMIFS(Clean_Daily!$J$2:$J$2107,Clean_Daily!$P$2:$P$2107,H3),SUMIFS(Clean_Daily!$J$2:$J$2107,Clean_Daily!$P$2:$P$2107,H3,Clean_Daily!$K$2:$K$2107,VALUE(Dashboard!$B$3))),IF(Dashboard!$B$3="All",SUMIFS(INDEX(Clean_Daily!$B$2:$I$2107,0,MATCH(Dashboard!$E$3,Clean_Daily!$B$1:$I$1,0)),Clean_Daily!$P$2:$P$2107,H3),SUMIFS(INDEX(Clean_Daily!$B$2:$I$2107,0,MATCH(Dashboard!$E$3,Clean_Daily!$B$1:$I$1,0)),Clean_Daily!$P$2:$P$2107,H3,Clean_Daily!$K$2:$K$2107,VALUE(Dashboard!$B$3))))/I3) -> 60.017432
A4: N02BA | B4: =IF(Dashboard!$B$3="All",SUM(Clean_Daily!D2:D2107),SUMIFS(Clean_Daily!D2:D2107,Clean_Daily!$K$2:$K$2107,VALUE(Dashboard!$B$3))) -> 8172.209 | C4: =IF(AND(B4=TRUE,OR(Dashboard!$B$3="All",YEAR(A4)=VALUE(Dashboard!$B$3))),IF(Dashboard!$E$3="All",SUMIFS(Clean_Daily!$J$2:$J$2107,Clean_Daily!$M$2:$M$2107,A4),SUMIFS(INDEX(Clean_Daily!$B$2:$I$2107,0,MATCH(Dashboard!$E$3,Clean_Daily!$B$1:$I$1,0)),Clean_Daily!$M$2:$M$2107,A4)),NA()) -> 1606.72 | H4: Wednesday | I4: =IF(Dashboard!$B$3="All",COUNTIF(Clean_Daily!$P$2:$P$2107,H4),COUNTIFS(Clean_Daily!$P$2:$P$2107,H4,Clean_Daily!$K$2:$K$2107,VALUE(Dashboard!$B$3))) -> 300 | J4: =IF(I4=0,0,IF(Dashboard!$E$3="All",IF(Dashboard!$B$3="All",SUMIFS(Clean_Daily!$J$2:$J$2107,Clean_Daily!$P$2:$P$2107,H4),SUMIFS(Clean_Daily!$J$2:$J$2107,Clean_Daily!$P$2:$P$2107,H4,Clean_Daily!$K$2:$K$2107,VALUE(Dashboard!$B$3))),IF(Dashboard!$B$3="All",SUMIFS(INDEX(Clean_Daily!$B$2:$I$2107,0,MATCH(Dashboard!$E$3,Clean_Daily!$B$1:$I$1,0)),Clean_Daily!$P$2:$P$2107,H4),SUMIFS(INDEX(Clean_Daily!$B$2:$I$2107,0,MATCH(Dashboard!$E$3,Clean_Daily!$B$1:$I$1,0)),Clean_Daily!$P$2:$P$2107,H4,Clean_Daily!$K$2:$K$2107,VALUE(Dashboard!$B$3))))/I4) -> 59.238425
A5: N02BE | B5: =IF(Dashboard!$B$3="All",SUM(Clean_Daily!E2:E2107),SUMIFS(Clean_Daily!E2:E2107,Clean_Daily!$K$2:$K$2107,VALUE(Dashboard!$B$3))) -> 63005.403 | C5: =IF(AND(B5=TRUE,OR(Dashboard!$B$3="All",YEAR(A5)=VALUE(Dashboard!$B$3))),IF(Dashboard!$E$3="All",SUMIFS(Clean_Daily!$J$2:$J$2107,Clean_Daily!$M$2:$M$2107,A5),SUMIFS(INDEX(Clean_Daily!$B$2:$I$2107,0,MATCH(Dashboard!$E$3,Clean_Daily!$B$1:$I$1,0)),Clean_Daily!$M$2:$M$2107,A5)),NA()) -> 1423.925 | H5: Thursday | I5: =IF(Dashboard!$B$3="All",COUNTIF(Clean_Daily!$P$2:$P$2107,H5),COUNTIFS(Clean_Daily!$P$2:$P$2107,H5,Clean_Daily!$K$2:$K$2107,VALUE(Dashboard!$B$3))) -> 301 | J5: =IF(I5=0,0,IF(Dashboard!$E$3="All",IF(Dashboard!$B$3="All",SUMIFS(Clean_Daily!$J$2:$J$2107,Clean_Daily!$P$2:$P$2107,H5),SUMIFS(Clean_Daily!$J$2:$J$2107,Clean_Daily!$P$2:$P$2107,H5,Clean_Daily!$K$2:$K$2107,VALUE(Dashboard!$B$3))),IF(Dashboard!$B$3="All",SUMIFS(INDEX(Clean_Daily!$B$2:$I$2107,0,MATCH(Dashboard!$E$3,Clean_Daily!$B$1:$I$1,0)),Clean_Daily!$P$2:$P$2107,H5),SUMIFS(INDEX(Clean_Daily!$B$2:$I$2107,0,MATCH(Dashboard!$E$3,Clean_Daily!$B$1:$I$1,0)),Clean_Daily!$P$2:$P$2107,H5,Clean_Daily!$K$2:$K$2107,VALUE(Dashboard!$B$3))))/I5) -> 57.184018
A6: N05B | B6: =IF(Dashboard!$B$3="All",SUM(Clean_Daily!F2:F2107),SUMIFS(Clean_Daily!F2:F2107,Clean_Daily!$K$2:$K$2107,VALUE(Dashboard!$B$3))) -> 18645.737 | C6: =IF(AND(B6=TRUE,OR(Dashboard!$B$3="All",YEAR(A6)=VALUE(Dashboard!$B$3))),IF(Dashboard!$E$3="All",SUMIFS(Clean_Daily!$J$2:$J$2107,Clean_Daily!$M$2:$M$2107,A6),SUMIFS(INDEX(Clean_Daily!$B$2:$I$2107,0,MATCH(Dashboard!$E$3,Clean_Daily!$B$1:$I$1,0)),Clean_Daily!$M$2:$M$2107,A6)),NA()) -> 1506.303 | H6: Friday | I6: =IF(Dashboard!$B$3="All",COUNTIF(Clean_Daily!$P$2:$P$2107,H6),COUNTIFS(Clean_Daily!$P$2:$P$2107,H6,Clean_Daily!$K$2:$K$2107,VALUE(Dashboard!$B$3))) -> 301 | J6: =IF(I6=0,0,IF(Dashboard!$E$3="All",IF(Dashboard!$B$3="All",SUMIFS(Clean_Daily!$J$2:$J$2107,Clean_Daily!$P$2:$P$2107,H6),SUMIFS(Clean_Daily!$J$2:$J$2107,Clean_Daily!$P$2:$P$2107,H6,Clean_Daily!$K$2:$K$2107,VALUE(Dashboard!$B$3))),IF(Dashboard!$B$3="All",SUMIFS(INDEX(Clean_Daily!$B$2:$I$2107,0,MATCH(Dashboard!$E$3,Clean_Daily!$B$1:$I$1,0)),Clean_Daily!$P$2:$P$2107,H6),SUMIFS(INDEX(Clean_Daily!$B$2:$I$2107,0,MATCH(Dashboard!$E$3,Clean_Daily!$B$1:$I$1,0)),Clean_Daily!$P$2:$P$2107,H6,Clean_Daily!$K$2:$K$2107,VALUE(Dashboard!$B$3))))/I6) -> 60.24748
A7: N05C | B7: =IF(Dashboard!$B$3="All",SUM(Clean_Daily!G2:G2107),SUMIFS(Clean_Daily!G2:G2107,Clean_Daily!$K$2:$K$2107,VALUE(Dashboard!$B$3))) -> 1249.9583 | C7: =IF(AND(B7=TRUE,OR(Dashboard!$B$3="All",YEAR(A7)=VALUE(Dashboard!$B$3))),IF(Dashboard!$E$3="All",SUMIFS(Clean_Daily!$J$2:$J$2107,Clean_Daily!$M$2:$M$2107,A7),SUMIFS(INDEX(Clean_Daily!$B$2:$I$2107,0,MATCH(Dashboard!$E$3,Clean_Daily!$B$1:$I$1,0)),Clean_Daily!$M$2:$M$2107,A7)),NA()) -> 1390.205 | H7: Saturday | I7: =IF(Dashboard!$B$3="All",COUNTIF(Clean_Daily!$P$2:$P$2107,H7),COUNTIFS(Clean_Daily!$P$2:$P$2107,H7,Clean_Daily!$K$2:$K$2107,VALUE(Dashboard!$B$3))) -> 301 | J7: =IF(I7=0,0,IF(Dashboard!$E$3="All",IF(Dashboard!$B$3="All",SUMIFS(Clean_Daily!$J$2:$J$2107,Clean_Daily!$P$2:$P$2107,H7),SUMIFS(Clean_Daily!$J$2:$J$2107,Clean_Daily!$P$2:$P$2107,H7,Clean_Daily!$K$2:$K$2107,VALUE(Dashboard!$B$3))),IF(Dashboard!$B$3="All",SUMIFS(INDEX(Clean_Daily!$B$2:$I$2107,0,MATCH(Dashboard!$E$3,Clean_Daily!$B$1:$I$1,0)),Clean_Daily!$P$2:$P$2107,H7),SUMIFS(INDEX(Clean_Daily!$B$2:$I$2107,0,MATCH(Dashboard!$E$3,Clean_Daily!$B$1:$I$1,0)),Clean_Daily!$P$2:$P$2107,H7,Clean_Daily!$K$2:$K$2107,VALUE(Dashboard!$B$3))))/I7) -> 65.673071
A8: R03 | B8: =IF(Dashboard!$B$3="All",SUM(Clean_Daily!H2:H2107),SUMIFS(Clean_Daily!H2:H2107,Clean_Daily!$K$2:$K$2107,VALUE(Dashboard!$B$3))) -> 11608.823 | C8: =IF(AND(B8=TRUE,OR(Dashboard!$B$3="All",YEAR(A8)=VALUE(Dashboard!$B$3))),IF(Dashboard!$E$3="All",SUMIFS(Clean_Daily!$J$2:$J$2107,Clean_Daily!$M$2:$M$2107,A8),SUMIFS(INDEX(Clean_Daily!$B$2:$I$2107,0,MATCH(Dashboard!$E$3,Clean_Daily!$B$1:$I$1,0)),Clean_Daily!$M$2:$M$2107,A8)),NA()) -> 1332.37 | H8: Sunday | I8: =IF(Dashboard!$B$3="All",COUNTIF(Clean_Daily!$P$2:$P$2107,H8),COUNTIFS(Clean_Daily!$P$2:$P$2107,H8,Clean_Daily!$K$2:$K$2107,VALUE(Dashboard!$B$3))) -> 301 | J8: =IF(I8=0,0,IF(Dashboard!$E$3="All",IF(Dashboard!$B$3="All",SUMIFS(Clean_Daily!$J$2:$J$2107,Clean_Daily!$P$2:$P$2107,H8),SUMIFS(Clean_Daily!$J$2:$J$2107,Clean_Daily!$P$2:$P$2107,H8,Clean_Daily!$K$2:$K$2107,VALUE(Dashboard!$B$3))),IF(Dashboard!$B$3="All",SUMIFS(INDEX(Clean_Daily!$B$2:$I$2107,0,MATCH(Dashboard!$E$3,Clean_Daily!$B$1:$I$1,0)),Clean_Daily!$P$2:$P$2107,H8),SUMIFS(INDEX(Clean_Daily!$B$2:$I$2107,0,MATCH(Dashboard!$E$3,Clean_Daily!$B$1:$I$1,0)),Clean_Daily!$P$2:$P$2107,H8,Clean_Daily!$K$2:$K$2107,VALUE(Dashboard!$B$3))))/I8) -> 61.134343
A9: R06 | B9: =IF(Dashboard!$B$3="All",SUM(Clean_Daily!I2:I2107),SUMIFS(Clean_Daily!I2:I2107,Clean_Daily!$K$2:$K$2107,VALUE(Dashboard!$B$3))) -> 6107.8175 | C9: =IF(AND(B9=TRUE,OR(Dashboard!$B$3="All",YEAR(A9)=VALUE(Dashboard!$B$3))),IF(Dashboard!$E$3="All",SUMIFS(Clean_Daily!$J$2:$J$2107,Clean_Daily!$M$2:$M$2107,A9),SUMIFS(INDEX(Clean_Daily!$B$2:$I$2107,0,MATCH(Dashboard!$E$3,Clean_Daily!$B$1:$I$1,0)),Clean_Daily!$M$2:$M$2107,A9)),NA()) -> 1452.52
A10: 41883 | B10: TRUE | C10: =IF(AND(B10=TRUE,OR(Dashboard!$B$3="All",YEAR(A10)=VALUE(Dashboard!$B$3))),IF(Dashboard!$E$3="All",SUMIFS(Clean_Daily!$J$2:$J$2107,Clean_Daily!$M$2:$M$2107,A10),SUMIFS(INDEX(Clean_Daily!$B$2:$I$2107,0,MATCH(Dashboard!$E$3,Clean_Daily!$B$1:$I$1,0)),Clean_Daily!$M$2:$M$2107,A10)),NA()) -> 1804.594
A11: 41913 | B11: TRUE | C11: =IF(AND(B11=TRUE,OR(Dashboard!$B$3="All",YEAR(A11)=VALUE(Dashboard!$B$3))),IF(Dashboard!$E$3="All",SUMIFS(Clean_Daily!$J$2:$J$2107,Clean_Daily!$M$2:$M$2107,A11),SUMIFS(INDEX(Clean_Daily!$B$2:$I$2107,0,MATCH(Dashboard!$E$3,Clean_Daily!$B$1:$I$1,0)),Clean_Daily!$M$2:$M$2107,A11)),NA()) -> 2081.9957
A12: 41944 | B12: TRUE | C12: =IF(AND(B12=TRUE,OR(Dashboard!$B$3="All",YEAR(A12)=VALUE(Dashboard!$B$3))),IF(Dashboard!$E$3="All",SUMIFS(Clean_Daily!$J$2:$J$2107,Clean_Daily!$M$2:$M$2107,A12),SUMIFS(INDEX(Clean_Daily!$B$2:$I$2107,0,MATCH(Dashboard!$E$3,Clean_Daily!$B$1:$I$1,0)),Clean_Daily!$M$2:$M$2107,A12)),NA()) -> 1770.64
A13: 41974 | B13: TRUE | C13: =IF(AND(B13=TRUE,OR(Dashboard!$B$3="All",YEAR(A13)=VALUE(Dashboard!$B$3))),IF(Dashboard!$E$3="All",SUMIFS(Clean_Daily!$J$2:$J$2107,Clean_Daily!$M$2:$M$2107,A13),SUMIFS(INDEX(Clean_Daily!$B$2:$I$2107,0,MATCH(Dashboard!$E$3,Clean_Daily!$B$1:$I$1,0)),Clean_Daily!$M$2:$M$2107,A13)),NA()) -> 2093.485
A14: 42005 | B14: TRUE | C14: =IF(AND(B14=TRUE,OR(Dashboard!$B$3="All",YEAR(A14)=VALUE(Dashboard!$B$3))),IF(Dashboard!$E$3="All",SUMIFS(Clean_Daily!$J$2:$J$2107,Clean_Daily!$M$2:$M$2107,A14),SUMIFS(INDEX(Clean_Daily!$B$2:$I$2107,0,MATCH(Dashboard!$E$3,Clean_Daily!$B$1:$I$1,0)),Clean_Daily!$M$2:$M$2107,A14)),NA()) -> 2157.749
A15: 42036 | B15: TRUE | C15: =IF(AND(B15=TRUE,OR(Dashboard!$B$3="All",YEAR(A15)=VALUE(Dashboard!$B$3))),IF(Dashboard!$E$3="All",SUMIFS(Clean_Daily!$J$2:$J$2107,Clean_Daily!$M$2:$M$2107,A15),SUMIFS(INDEX(Clean_Daily!$B$2:$I$2107,0,MATCH(Dashboard!$E$3,Clean_Daily!$B$1:$I$1,0)),Clean_Daily!$M$2:$M$2107,A15)),NA()) -> 1831.532
A16: 42064 | B16: TRUE | C16: =IF(AND(B16=TRUE,OR(Dashboard!$B$3="All",YEAR(A16)=VALUE(Dashboard!$B$3))),IF(Dashboard!$E$3="All",SUMIFS(Clean_Daily!$J$2:$J$2107,Clean_Daily!$M$2:$M$2107,A16),SUMIFS(INDEX(Clean_Daily!$B$2:$I$2107,0,MATCH(Dashboard!$E$3,Clean_Daily!$B$1:$I$1,0)),Clean_Daily!$M$2:$M$2107,A16)),NA()) -> 1949.076
A17: 42095 | B17: TRUE | C17: =IF(AND(B17=TRUE,OR(Dashboard!$B$3="All",YEAR(A17)=VALUE(Dashboard!$B$3))),IF(Dashboard!$E$3="All",SUMIFS(Clean_Daily!$J$2:$J$2107,Clean_Daily!$M$2:$M$2107,A17),SUMIFS(INDEX(Clean_Daily!$B$2:$I$2107,0,MATCH(Dashboard!$E$3,Clean_Daily!$B$1:$I$1,0)),Clean_Daily!$M$2:$M$2107,A17)),NA()) -> 1723.885
A18: 42125 | B18: TRUE | C18: =IF(AND(B18=TRUE,OR(Dashboard!$B$3="All",YEAR(A18)=VALUE(Dashboard!$B$3))),IF(Dashboard!$E$3="All",SUMIFS(Clean_Daily!$J$2:$J$2107,Clean_Daily!$M$2:$M$2107,A18),SUMIFS(INDEX(Clean_Daily!$B$2:$I$2107,0,MATCH(Dashboard!$E$3,Clean_Daily!$B$1:$I$1,0)),Clean_Daily!$M$2:$M$2107,A18)),NA()) -> 1644.577
A19: 42156 | B19: TRUE | C19: =IF(AND(B19=TRUE,OR(Dashboard!$B$3="All",YEAR(A19)=VALUE(Dashboard!$B$3))),IF(Dashboard!$E$3="All",SUMIFS(Clean_Daily!$J$2:$J$2107,Clean_Daily!$M$2:$M$2107,A19),SUMIFS(INDEX(Clean_Daily!$B$2:$I$2107,0,MATCH(Dashboard!$E$3,Clean_Daily!$B$1:$I$1,0)),Clean_Daily!$M$2:$M$2107,A19)),NA()) -> 1674.233
A20: 42186 | B20: TRUE | C20: =IF(AND(B20=TRUE,OR(Dashboard!$B$3="All",YEAR(A20)=VALUE(Dashboard!$B$3))),IF(Dashboard!$E$3="All",SUMIFS(Clean_Daily!$J$2:$J$2107,Clean_Daily!$M$2:$M$2107,A20),SUMIFS(INDEX(Clean_Daily!$B$2:$I$2107,0,MATCH(Dashboard!$E$3,Clean_Daily!$B$1:$I$1,0)),Clean_Daily!$M$2:$M$2107,A20)),NA()) -> 1523.048
A21: 42217 | B21: TRUE | C21: =IF(AND(B21=TRUE,OR(Dashboard!$B$3="All",YEAR(A21)=VALUE(Dashboard!$B$3))),IF(Dashboard!$E$3="All",SUMIFS(Clean_Daily!$J$2:$J$2107,Clean_Daily!$M$2:$M$2107,A21),SUMIFS(INDEX(Clean_Daily!$B$2:$I$2107,0,MATCH(Dashboard!$E$3,Clean_Daily!$B$1:$I$1,0)),Clean_Daily!$M$2:$M$2107,A21)),NA()) -> 1659.597
... A71: 43739 | B71: FALSE | C71: =IF(AND(B71=TRUE,OR(Dashboard!$B$3="All",YEAR(A71)=VALUE(Dashboard!$B$3))),IF(Dashboard!$E$3="All",SUMIFS(Clean_Daily!$J$2:$J$2107,Clean_Daily!$M$2:$M$2107,A71),SUMIFS(INDEX(Clean_Daily!$B$2:$I$2107,0,MATCH(Dashboard!$E$3,Clean_Daily!$B$1:$I$1,0)),Clean_Daily!$M$2:$M$2107,A71)),NA()) -> #N/A

Sheet Dashboard
A1: PHARMACEUTICAL SALES DASHBOARD
A3: YEAR | B3: All | D3: CATEGORY | E3: All | G3: Yellow cells are drop-down controls. Open in desktop Excel and allow automatic calculation.
A5: TOTAL QUANTITY | E5: AVERAGE DAILY QUANTITY | I5: DAYS IN SELECTION | M5: OVERALL LEADING CATEGORY
A6: =IF($E$3="All",IF($B$3="All",SUM(Clean_Daily!$J$2:$J$2107),SUMIFS(Clean_Daily!$J$2:$J$2107,Clean_Daily!$K$2:$K$2107,VALUE($B$3))),IF($B$3="All",SUM(INDEX(Clean_Daily!$B$2:$I$2107,0,MATCH($E$3,Clean_Daily!$B$1:$I$1,0))),SUMIFS(INDEX(Clean_Daily!$B$2:$I$2107,0,MATCH($E$3,Clean_Daily!$B$1:$I$1,0)),Clean_Daily!$K$2:$K$2107,VALUE($B$3)))) -> 127595.5 | E6: =IF($E$3="All",IF($B$3="All",AVERAGE(Clean_Daily!$J$2:$J$2107),AVERAGEIF(Clean_Daily!$K$2:$K$2107,VALUE($B$3),Clean_Daily!$J$2:$J$2107)),IF($B$3="All",AVERAGE(INDEX(Clean_Daily!$B$2:$I$2107,0,MATCH($E$3,Clean_Daily!$B$1:$I$1,0))),AVERAGEIF(Clean_Daily!$K$2:$K$2107,VALUE($B$3),INDEX(Clean_Daily!$B$2:$I$2107,0,MATCH($E$3,Clean_Daily!$B$1:$I$1,0))))) -> 60.586659 | I6: =IF($B$3="All",COUNT(Clean_Daily!$A$2:$A$2107),COUNTIF(Clean_Daily!$K$2:$K$2107,VALUE($B$3))) -> 2106 | M6: N02BE 49.38% of total
A9: ="Selection: "&$B$3&" | "&$E$3&" • Monthly trend excludes partial Jan 2014 and Oct 2019 • Quantity is not revenue" -> Selection: All | All • Monthly trend excludes partial Jan 2014 and Oct 2019 • Quantity is not revenue
I11: OVERALL KEY FINDINGS (ALL DATA) • N02BE contributes 49.38% of all recorded quantity. • The top three categories contribute 73.09%. • January 2019 is the highest complete month: 2,875.16. • Saturday has the highest weekday average: 65.67 per day.
I18: INVENTORY INTERPRETATION Use these values as historical demand evidence only. Before ordering, add current stock, supplier lead time, minimum order quantity, expiry risk, local prescriptions and pharmacist review. N05C and R03 have many zero days, so a simple average alone is not enough.
I24: Native PivotTables and application screenshots still need to be created/captured in the relevant software. See the step-by-step guides in this package.
